MANIFEST.in
README.md
setup.py
opclabs_mqtt/__init__.py
opclabs_mqtt.egg-info/PKG-INFO
opclabs_mqtt.egg-info/SOURCES.txt
opclabs_mqtt.egg-info/dependency_links.txt
opclabs_mqtt.egg-info/not-zip-safe
opclabs_mqtt.egg-info/requires.txt
opclabs_mqtt.egg-info/top_level.txt
opclabs_mqtt/OpcLabs.Mqtt/Microsoft.NETCore.Platforms_1.0.1.txt
opclabs_mqtt/OpcLabs.Mqtt/Microsoft.NETCore.Platforms_1.1.0.txt
opclabs_mqtt/OpcLabs.Mqtt/Microsoft.NETCore.Targets_1.0.1.txt
opclabs_mqtt/OpcLabs.Mqtt/Microsoft.NETCore.Targets_1.1.0.txt
opclabs_mqtt/OpcLabs.Mqtt/System.Collections.Concurrent_4.0.12.txt
opclabs_mqtt/OpcLabs.Mqtt/System.Collections_4.0.11.txt
opclabs_mqtt/OpcLabs.Mqtt/System.ComponentModel_4.0.1.txt
opclabs_mqtt/OpcLabs.Mqtt/System.Diagnostics.Contracts_4.3.0.txt
opclabs_mqtt/OpcLabs.Mqtt/System.Diagnostics.Debug_4.0.11.txt
opclabs_mqtt/OpcLabs.Mqtt/System.Diagnostics.Tools_4.0.1.txt
opclabs_mqtt/OpcLabs.Mqtt/System.Diagnostics.TraceSource_4.0.0.txt
opclabs_mqtt/OpcLabs.Mqtt/System.Diagnostics.Tracing_4.1.0.txt
opclabs_mqtt/OpcLabs.Mqtt/System.Dynamic.Runtime_4.0.11.txt
opclabs_mqtt/OpcLabs.Mqtt/System.Globalization_4.0.11.txt
opclabs_mqtt/OpcLabs.Mqtt/System.IO_4.1.0.txt
opclabs_mqtt/OpcLabs.Mqtt/System.Linq.Expressions_4.1.0.txt
opclabs_mqtt/OpcLabs.Mqtt/System.Linq_4.1.0.txt
opclabs_mqtt/OpcLabs.Mqtt/System.Net.Mqtt_0.6.0-beta.txt
opclabs_mqtt/OpcLabs.Mqtt/System.ObjectModel_4.0.12.txt
opclabs_mqtt/OpcLabs.Mqtt/System.Reactive.Core_3.0.0.txt
opclabs_mqtt/OpcLabs.Mqtt/System.Reactive.Interfaces_3.0.0.txt
opclabs_mqtt/OpcLabs.Mqtt/System.Reactive.Linq_3.0.0.txt
opclabs_mqtt/OpcLabs.Mqtt/System.Reactive.PlatformServices_3.0.0.txt
opclabs_mqtt/OpcLabs.Mqtt/System.Reactive.Windows.Threading_3.0.0.txt
opclabs_mqtt/OpcLabs.Mqtt/System.Reactive.WindowsRuntime_3.0.0.txt
opclabs_mqtt/OpcLabs.Mqtt/System.Reactive_3.0.0.txt
opclabs_mqtt/OpcLabs.Mqtt/System.Reflection.Emit.ILGeneration_4.0.1.txt
opclabs_mqtt/OpcLabs.Mqtt/System.Reflection.Emit.Lightweight_4.0.1.txt
opclabs_mqtt/OpcLabs.Mqtt/System.Reflection.Emit_4.0.1.txt
opclabs_mqtt/OpcLabs.Mqtt/System.Reflection.Extensions_4.0.1.txt
opclabs_mqtt/OpcLabs.Mqtt/System.Reflection.Primitives_4.0.1.txt
