Metadata-Version: 2.4
Name: opclabs_mqtt
Version: 5.83.1043
Summary: MQTT communication package based on System.Net.Mqtt library by Xamarin (Microsoft).
Home-page: https://kb.opclabs.com/OpcLabs.Mqtt_communication_package?python
Author: CODE Consulting and Development, s.r.o.
Author-email: sales09@opclabs.com
Keywords: QuickOPC,OPC,UA,PubSub,MQTT
License-File: opclabs_mqtt/OpcLabs.Mqtt/Microsoft.NETCore.Platforms_1.0.1.txt
License-File: opclabs_mqtt/OpcLabs.Mqtt/Microsoft.NETCore.Platforms_1.1.0.txt
License-File: opclabs_mqtt/OpcLabs.Mqtt/Microsoft.NETCore.Targets_1.0.1.txt
License-File: opclabs_mqtt/OpcLabs.Mqtt/Microsoft.NETCore.Targets_1.1.0.txt
License-File: opclabs_mqtt/OpcLabs.Mqtt/System.Collections.Concurrent_4.0.12.txt
License-File: opclabs_mqtt/OpcLabs.Mqtt/System.Collections_4.0.11.txt
License-File: opclabs_mqtt/OpcLabs.Mqtt/System.ComponentModel_4.0.1.txt
License-File: opclabs_mqtt/OpcLabs.Mqtt/System.Diagnostics.Contracts_4.3.0.txt
License-File: opclabs_mqtt/OpcLabs.Mqtt/System.Diagnostics.Debug_4.0.11.txt
License-File: opclabs_mqtt/OpcLabs.Mqtt/System.Diagnostics.Tools_4.0.1.txt
License-File: opclabs_mqtt/OpcLabs.Mqtt/System.Diagnostics.TraceSource_4.0.0.txt
License-File: opclabs_mqtt/OpcLabs.Mqtt/System.Diagnostics.Tracing_4.1.0.txt
License-File: opclabs_mqtt/OpcLabs.Mqtt/System.Dynamic.Runtime_4.0.11.txt
License-File: opclabs_mqtt/OpcLabs.Mqtt/System.Globalization_4.0.11.txt
License-File: opclabs_mqtt/OpcLabs.Mqtt/System.IO_4.1.0.txt
License-File: opclabs_mqtt/OpcLabs.Mqtt/System.Linq.Expressions_4.1.0.txt
License-File: opclabs_mqtt/OpcLabs.Mqtt/System.Linq_4.1.0.txt
License-File: opclabs_mqtt/OpcLabs.Mqtt/System.Net.Mqtt_0.6.0-beta.txt
License-File: opclabs_mqtt/OpcLabs.Mqtt/System.ObjectModel_4.0.12.txt
License-File: opclabs_mqtt/OpcLabs.Mqtt/System.Reactive.Core_3.0.0.txt
License-File: opclabs_mqtt/OpcLabs.Mqtt/System.Reactive.Interfaces_3.0.0.txt
License-File: opclabs_mqtt/OpcLabs.Mqtt/System.Reactive.Linq_3.0.0.txt
License-File: opclabs_mqtt/OpcLabs.Mqtt/System.Reactive.PlatformServices_3.0.0.txt
License-File: opclabs_mqtt/OpcLabs.Mqtt/System.Reactive.Windows.Threading_3.0.0.txt
License-File: opclabs_mqtt/OpcLabs.Mqtt/System.Reactive.WindowsRuntime_3.0.0.txt
License-File: opclabs_mqtt/OpcLabs.Mqtt/System.Reactive_3.0.0.txt
License-File: opclabs_mqtt/OpcLabs.Mqtt/System.Reflection.Emit.ILGeneration_4.0.1.txt
License-File: opclabs_mqtt/OpcLabs.Mqtt/System.Reflection.Emit.Lightweight_4.0.1.txt
License-File: opclabs_mqtt/OpcLabs.Mqtt/System.Reflection.Emit_4.0.1.txt
License-File: opclabs_mqtt/OpcLabs.Mqtt/System.Reflection.Extensions_4.0.1.txt
License-File: opclabs_mqtt/OpcLabs.Mqtt/System.Reflection.Primitives_4.0.1.txt
License-File: opclabs_mqtt/OpcLabs.Mqtt/System.Reflection.TypeExtensions_4.1.0.txt
License-File: opclabs_mqtt/OpcLabs.Mqtt/System.Reflection_4.1.0.txt
License-File: opclabs_mqtt/OpcLabs.Mqtt/System.Resources.ResourceManager_4.0.1.txt
License-File: opclabs_mqtt/OpcLabs.Mqtt/System.Runtime.Extensions_4.1.0.txt
License-File: opclabs_mqtt/OpcLabs.Mqtt/System.Runtime.Handles_4.0.1.txt
License-File: opclabs_mqtt/OpcLabs.Mqtt/System.Runtime.InteropServices.WindowsRuntime_4.0.1.txt
License-File: opclabs_mqtt/OpcLabs.Mqtt/System.Runtime.InteropServices_4.1.0.txt
License-File: opclabs_mqtt/OpcLabs.Mqtt/System.Runtime.Serialization.Primitives_4.1.1.txt
License-File: opclabs_mqtt/OpcLabs.Mqtt/System.Runtime.WindowsRuntime_4.0.11.txt
License-File: opclabs_mqtt/OpcLabs.Mqtt/System.Runtime_4.1.0.txt
License-File: opclabs_mqtt/OpcLabs.Mqtt/System.Runtime_4.3.0.txt
License-File: opclabs_mqtt/OpcLabs.Mqtt/System.Text.Encoding_4.0.11.txt
License-File: opclabs_mqtt/OpcLabs.Mqtt/System.Threading.Tasks_4.0.11.txt
License-File: opclabs_mqtt/OpcLabs.Mqtt/System.Threading.ThreadPool_4.0.10.txt
License-File: opclabs_mqtt/OpcLabs.Mqtt/System.Threading.Thread_4.0.0.txt
License-File: opclabs_mqtt/OpcLabs.Mqtt/System.Threading.Timer_4.0.1.txt
License-File: opclabs_mqtt/OpcLabs.Mqtt/System.Threading_4.0.11.txt
License-File: opclabs_mqtt/OpcLabs.Mqtt/runtime.native.System_4.0.0.txt
Requires-Dist: opclabs_quickopc
Dynamic: author
Dynamic: author-email
Dynamic: description
Dynamic: description-content-type
Dynamic: home-page
Dynamic: keywords
Dynamic: license-file
Dynamic: requires-dist
Dynamic: summary
